juicefs/__init__.py
juicefs/io.py
juicefs/juicefs.py
juicefs/libjfs.py
juicefs/utils.py
juicefs/version.py
juicefs/lib/__init__.py
juicefs/lib/juicefs
juicefs/lib/libjfs.so
juicefs-0.0.4.dist-info/LICENSE
juicefs-0.0.4.dist-info/METADATA
juicefs-0.0.4.dist-info/WHEEL
juicefs-0.0.4.dist-info/top_level.txt
juicefs-0.0.4.dist-info/RECORD
